Workbook

Sheet 0_Instrucciones
A1: DURACIÓN DE CARTERAS DE SEGUROS — EJERCICIO ACTUARIAL
C3: Diplomado ML en Seguros · Módulo: Reservas y Gestión de Activos y Pasivos
A5: PROPÓSITO | C5: Calcular las tres medidas de duración (Macaulay, Modificada y Efectiva)
C6: para dos carteras: Auto Daños RC Personal y Crédito/Caución.
A8: REFERENCIAS | C8: D'Arcy & Gorvett (2000). The Effective Duration and Convexity of P-L Liabilities. PCAS.
C9: Hodes & Feldblum (1996). Interest Rate Risk and Capital Requirements. Proc. CAS 83.
C10: Macaulay, F. (1938). Movement of Interest Rates, Bond Yields and Stock Prices. NBER.
A12: HOJAS | B12: 1_Auto_Duration | C12: Cartera de Auto Daños RC Personal — patrón de 10 años
B14: 2_Credito_Duration | C14: Cartera de Crédito / Caución — patrón de 4 años con recovery
B16: 3_Comparacion | C16: Resumen comparativo y análisis de sensibilidad
A18: CELDAS AMARILLAS → | C18: Parámetros que puedes modificar (tasa, reserva, patrón de pago)
A19: CELDAS BLANCAS c/ fórmula → | C19: Calculadas automáticamente — no modificar
A20: CELDAS VERDES → | C20: Resultados finales de duración
A22: FÓRMULAS CLAVE | C22: D_Macaulay = Σ[t × PV(CF_t)] / Σ[PV(CF_t)]
C23: D_Modificada = D_Macaulay / (1 + r)
C24: D_Efectiva = (PV₋ - PV₊) / (2 × PV₀ × Δr) [numérica, ±100 bps]
C25: Convexidad = Σ[t(t+1) × PV(CF_t) / (1+r)²] / PV_Total
A27: VALIDACIÓN | C27: Los resultados de Auto deben aproximarse a: D_Mac≈1.5, D_Mod≈1.4, D_Ef≈1.1
B28: Parámetro de entrada (modificable)
B29: Resultado de duración
B30: Fórmula calculada

Sheet 1_Auto_Duration
B1: DURACIÓN DE CARTERA — AUTO DAÑOS / RC PERSONAL
B2: Metodología: Macaulay · Modificada · Efectiva | Fuente: D'Arcy & Gorvett (2000), PCAS
B4: PARÁMETROS DE ENTRADA
B5: Reserva total (MXN) | C5: 1000000 | D5: Monto total de la reserva IBNR a valuar
B6: Tasa de descuento (r) | C6: 0.05 | D6: Tasa libre de riesgo (CETES / curva CNSF) | J6: 0.04
B7: Shock de tasa (Δr) | C7: 0.01 | D7: Desplazamiento para calcular duración efectiva (±100 bps)
B8: Correlación tasas-inflación | C8: 0.4 | D8: ρ: usada para ajustar D_Efectiva (D'Arcy 2000, Tabla 3)
B10: A. PATRÓN DE DESARROLLO Y FLUJOS DE PAGO
B11: Año (t) | C11: % Pago Acumulado | D11: % Pago Incremental | E11: Flujo Nominal (MXN) | F11: PV del Flujo (MXN) | G11: Peso = PV/PV_Total | H11: t × Peso | I11: t(t+1)×PV/(1+r)² (Convexidad)
B12: 1 | C12: 0.386 | D12: =C12 -> 0.386 | E12: =D12*$C$5 -> 386000 | F12: =E12/(1+$C$6)^B12 -> 367619.05 | G12: =F12/F22 -> 0.41047816 | H12: =B12*G12 -> 0.41047816 | I12: =B12*(B12+1)*F12/((1+$C$6)^2)/F22 -> 0.74463159 | J12: =+B12*F12 -> 367619.05
B13: 2 | C13: 0.701 | D13: =C13-C12 -> 0.315 | E13: =D13*$C$5 -> 315000 | F13: =E13/(1+$C$6)^B13 -> 285714.29 | G13: =F13/F22 -> 0.31902448 | H13: =B13*G13 -> 0.63804896 | I13: =B13*(B13+1)*F13/((1+$C$6)^2)/F22 -> 1.7361876 | J13: =+B13*F13 -> 571428.57
B14: 3 | C14: 0.843 | D14: =C14-C13 -> 0.142 | E14: =D14*$C$5 -> 142000 | F14: =E14/(1+$C$6)^B14 -> 122664.94 | G14: =F14/F22 -> 0.13696591 | H14: =B14*G14 -> 0.41089774 | I14: =B14*(B14+1)*F14/((1+$C$6)^2)/F22 -> 1.4907855 | J14: =+B14*F14 -> 367994.82
B15: 4 | C15: 0.919 | D15: =C15-C14 -> 0.076 | E15: =D15*$C$5 -> 76000 | F15: =E15/(1+$C$6)^B15 -> 62525.388 | G15: =F15/F22 -> 0.069814953 | H15: =B15*G15 -> 0.27925981 | I15: =B15*(B15+1)*F15/((1+$C$6)^2)/F22 -> 1.2664844 | J15: =+B15*F15 -> 250101.55
B16: 5 | C16: 0.958 | D16: =C16-C15 -> 0.039 | E16: =D16*$C$5 -> 39000 | F16: =E16/(1+$C$6)^B16 -> 30557.52 | G16: =F16/F22 -> 0.03412009 | H16: =B16*G16 -> 0.17060045 | I16: =B16*(B16+1)*F16/((1+$C$6)^2)/F22 -> 0.92843782 | J16: =+B16*F16 -> 152787.6
B17: 6 | C17: 0.977 | D17: =C17-C16 -> 0.019 | E17: =D17*$C$5 -> 19000 | F17: =E17/(1+$C$6)^B17 -> 14178.093 | G17: =F17/F22 -> 0.015831055 | H17: =B17*G17 -> 0.09498633 | I17: =B17*(B17+1)*F17/((1+$C$6)^2)/F22 -> 0.60308781 | J17: =+B17*F17 -> 85068.555
B18: 7 | C18: 0.986 | D18: =C18-C17 -> 0.009 | E18: =D18*$C$5 -> 9000 | F18: =E18/(1+$C$6)^B18 -> 6396.132 | G18: =F18/F22 -> 0.0071418294 | H18: =B18*G18 -> 0.049992805 | I18: =B18*(B18+1)*F18/((1+$C$6)^2)/F22 -> 0.36275959 | J18: =+B18*F18 -> 44772.924
B19: 8 | C19: 0.991 | D19: =C19-C18 -> 0.005 | E19: =D19*$C$5 -> 5000 | F19: =E19/(1+$C$6)^B19 -> 3384.1968 | G19: =F19/F22 -> 0.0037787457 | H19: =B19*G19 -> 0.030229966 | I19: =B19*(B19+1)*F19/((1+$C$6)^2)/F22 -> 0.24677523 | J19: =+B19*F19 -> 27073.574
B20: 9 | C20: 0.994 | D20: =C20-C19 -> 0.003 | E20: =D20*$C$5 -> 3000 | F20: =E20/(1+$C$6)^B20 -> 1933.8267 | G20: =F20/F22 -> 0.0021592833 | H20: =B20*G20 -> 0.019433549 | I20: =B20*(B20+1)*F20/((1+$C$6)^2)/F22 -> 0.17626802 | J20: =+B20*F20 -> 17404.441
B21: 10 | C21: 0.995 | D21: =C21-C20 -> 0.001 | E21: =D21*$C$5 -> 1000 | F21: =E21/(1+$C$6)^B21 -> 613.91325 | G21: =F21/F22 -> 0.00068548675 | H21: =B21*G21 -> 0.0068548675 | I21: =B21*(B21+1)*F21/((1+$C$6)^2)/F22 -> 0.068393235 | J21: =+B21*F21 -> 6139.1325
B22: TOTAL | C22: 100.00% | E22: =SUM(E12:E21) -> 995000 | F22: =SUM(F12:F21) -> 895587.34 | G22: =SUM(G12:G21) -> 1 | H22: =SUM(H12:H21) -> 2.1107826 | J22: =SUM(J12:J21) -> 1890390.2 | K22: =+J22/F22 -> 2.1107826
F23: 895587.34
B24: B. CÁLCULO DE DURACIÓN
B25: Duración de Macaulay (D_Mac) | C25: =SUMPRODUCT(B12:B21,F12:F21)/F22 -> 2.1107826 | D25: años | E25: D_Mac = Σ[t × PV(CF_t)] / PV_Total | H25: ~1.5 años (D'Arcy 2000 reporta 1.516 para PPA empírico)
B27: Duración Modificada (D_Mod) | C27: =(SUMPRODUCT(B12:B21,F12:F21)/F22)/(1+C6) -> 2.0102692 | D27: años | E27: D_Mod = D_Mac / (1 + r) | H27: ~1.44 años (D'Arcy 2000 reporta 1.444) | J27: =+K22/(1+C6) -> 2.0102692
B29: Convexidad | C29: =SUMPRODUCT(B12:B21*(B12:B21+1),F12:F21)/((1+C6)^2*F22) -> 7.6238108 | E29: Conv = Σ[t(t+1)×PV(CF_t)/PV_Total] / (1+r)² | H29: Curvatura de la función PV vs tasa
B31: Duración Efectiva (D_Ef) — numérica | C31: {=(SUMPRODUCT(D12:D21*$C$5,1/((1+$C$6-$C$7)^(B12:B21)))-SUMPRODUCT(D12:D21*$C$5,1/((1+$C$6+$C$7)^(B12:B21))))/(2*F22*$C$7)} -> 2.0109686 | D31: años | E31: D_Ef = (PV_baja − PV_sube) / (2 × PV₀ × Δr) | H31: ~1.09 años (D'Arcy 2000 reporta 1.089, correlación ρ=40%) | J31: {=+SUMPRODUCT(D12:D21*$C$5,1/((1+$C$6-$C$7)^(B12:B21)))} -> 913938.82 | K31: {=+SUMPRODUCT(D12:D21*$C$5,1/((1+$C$6+$C$7)^(B12:B21)))} -> 877918.86
B32: D_Ef ajustada por correlación i-inflación | C32: =C31*(1-C8*0.62) -> 1.5122484 | D32: años | E32: D_Ef = D_Mod × (1 − ρ × 0.62) donde ρ=correlación tasas-inflación | H32: Paper: D_Ef ≈ D_Mod × 0.754 con ρ=40%. Factor 0.62 calibrado al paper.
B34: C. ANÁLISIS DE SENSIBILIDAD — Δ PV ante cambios de tasa
B35: Escenario | C35: Tasa aplicada | D35: PV de Pasivos | E35: Δ PV vs base | F35: Δ PV % | G35: D_Mod × Δr (aprox.)
B36: Tasa base (r) | C36: =C6 -> 0.05 | D36: =SUMPRODUCT(D12:D21*$C$5,1/((1+C36)^B12:B21)) -> 895587.34 | E36: — | F36: — | G36: —
B37: Sube 100 bps | C37: =C6+C7 -> 0.06 | D37: =SUMPRODUCT(D12:D21*$C$5,1/((1+C37)^B12:B21)) -> 877918.86 | E37: =D37-D36 -> -17668.479 | F37: =E37/D36 -> -0.01972837 | G37: =-C27*(C37-$C$6)*D36 -> -18003.716
B38: Sube 200 bps | C38: =C6+2*C7 -> 0.07 | D38: =SUMPRODUCT(D12:D21*$C$5,1/((1+C38)^B12:B21)) -> 860897.1 | E38: =D38-D36 -> -34690.238 | F38: =E38/D36 -> -0.038734623 | G38: =-C27*(C38-$C$6)*D36 -> -36007.433
B39: Baja 100 bps | C39: =C6-C7 -> 0.04 | D39: =SUMPRODUCT(D12:D21*$C$5,1/((1+C39)^B12:B21)) -> 913938.82 | E39: =D39-D36 -> 18351.481 | F39: =E39/D36 -> 0.020491001 | G39: =-C27*(C39-$C$6)*D36 -> 18003.716
B40: Baja 200 bps | C40: =C6-2*C7 -> 0.03 | D40: =SUMPRODUCT(D12:D21*$C$5,1/((1+C40)^B12:B21)) -> 933012.28 | E40: =D40-D36 -> 37424.939 | F40: =E40/D36 -> 0.041788151 | G40: =-C27*(C40-$C$6)*D36 -> 36007.433

Sheet 2_Credito_Duration
B1: DURACIÓN DE CARTERA — CRÉDITO / CAUCIÓN
B2: Metodología: Macaulay · Modificada · Efectiva | Ajuste por Recovery Rate y Prob. Default
B4: PARÁMETROS DE ENTRADA
B5: Reserva total (MXN) | C5: 500000 | D5: Monto total de la reserva de crédito
B6: Tasa de descuento (r) | C6: 0.06 | D6: Spread por riesgo crédito incluido en la tasa
B7: Shock de tasa (Δr) | C7: 0.01 | D7: Desplazamiento ±100 bps para D_Efectiva
B8: Tasa de recuperación (LGD) | C8: 0.4 | D8: Loss Given Default = 1 - Recovery Rate esperada
B9: Prob. de default anual (PD) | C9: 0.03 | D9: Probabilidad anual de default del portafolio
B10: ⚠️ NOTA: En crédito la duración mide la sensibilidad del VALOR PRESENTE de las PÉRDIDAS ESPERADAS ante cambios en la tasa de descuento. El flujo neto de cada período = Flujo bruto × (1 − Recovery). A diferencia de auto, la duración efectiva ≈ modificada porque los flujos de crédito no son sensibles a la inflación (sino al ciclo económico). Referencia: Noris (1985), Morgan Stanley.
B12: A. PATRÓN DE PAGO Y FLUJOS NETOS (ajustados por Recovery)
B13: Año (t) | C13: % Pago Acumulado | D13: % Pago Incremental | E13: Flujo Bruto (MXN) | F13: Factor Neto (1−Recovery) | G13: Flujo Neto (MXN) | H13: PV Flujo Neto (MXN) | I13: Peso=PV/PV_Total | J13: t × Peso | K13: t(t+1)×PV /(1+r)²
B14: 1 | C14: 0.5 | D14: =C14 -> 0.5 | E14: =D14*$C$5 -> 250000 | F14: =1-$C$8 -> 0.6 | G14: =E14*F14 -> 150000 | H14: =G14/(1+$C$6)^B14 -> 141509.43 | I14: =H14/H18 -> 0.52164879 | J14: =B14*I14 -> 0.52164879 | K14: =B14*(B14+1)*H14/((1+$C$6)^2)/H18 -> 0.92853113
B15: 2 | C15: 0.8 | D15: =C15-C14 -> 0.3 | E15: =D15*$C$5 -> 150000 | F15: =1-$C$8 -> 0.6 | G15: =E15*F15 -> 90000 | H15: =G15/(1+$C$6)^B15 -> 80099.68 | I15: =H15/H18 -> 0.2952729 | J15: =B15*I15 -> 0.5905458 | K15: =B15*(B15+1)*H15/((1+$C$6)^2)/H18 -> 1.576751
B16: 3 | C16: 0.95 | D16: =C16-C15 -> 0.15 | E16: =D16*$C$5 -> 75000 | F16: =1-$C$8 -> 0.6 | G16: =E16*F16 -> 45000 | H16: =G16/(1+$C$6)^B16 -> 37782.868 | I16: =H16/H18 -> 0.13927967 | J16: =B16*I16 -> 0.41783901 | K16: =B16*(B16+1)*H16/((1+$C$6)^2)/H18 -> 1.4875009
B17: 4 | C17: 1 | D17: =C17-C16 -> 0.05 | E17: =D17*$C$5 -> 25000 | F17: =1-$C$8 -> 0.6 | G17: =E17*F17 -> 15000 | H17: =G17/(1+$C$6)^B17 -> 11881.405 | I17: =H17/H18 -> 0.043798638 | J17: =B17*I17 -> 0.17519455 | K17: =B17*(B17+1)*H17/((1+$C$6)^2)/H18 -> 0.77961264
B18: TOTAL | C18: 100.00% | E18: =SUM(E14:E17) -> 500000 | G18: =SUM(G14:G17) -> 300000 | H18: =SUM(H14:H17) -> 271273.39 | I18: =SUM(I14:I17) -> 1
B20: B. CÁLCULO DE DURACIÓN
B21: Duración de Macaulay (D_Mac) | C21: =SUMPRODUCT(B14:B17,H14:H17)/H18 -> 1.7052282 | D21: años | E21: D_Mac = Σ[t × PV(CF_neto_t)] / PV_Total_Neto | H21: Rango típico crédito: 1.0–3.0 años (cola corta, Noris 1985)
B23: Duración Modificada (D_Mod) | C23: =(SUMPRODUCT(B14:B17,H14:H17)/H18)/(1+C6) -> 1.6087058 | D23: años | E23: D_Mod = D_Mac / (1 + r) | H23: En crédito: D_Ef ≈ D_Mod (flujos no sensibles a inflación)
B25: Convexidad | C25: =SUMPRODUCT(B14:B17*(B14:B17+1),H14:H17)/((1+C6)^2*H18) -> 4.7723957 | E25: Conv = Σ[t(t+1)×PV_neto] / [(1+r)² × PV_Total]
B27: Duración Efectiva (D_Ef) — numérica | C27: {=(SUMPRODUCT(D14:D17*$C$5*(1-$C$8),1/((1+$C$6-$C$7)^(B14:B17)))-SUMPRODUCT(D14:D17*$C$5*(1-$C$8),1/((1+$C$6+$C$7)^(B14:B17))))/(2*H18*$C$7)} -> 1.6090393 | D27: años | E27: D_Ef = (PV_baja − PV_sube) / (2 × PV₀ × Δr) | H27: Para crédito: D_Ef ≈ D_Mod porque ρ(i, inflación_crédito) ≈ 0
B30: C. ANÁLISIS DE SENSIBILIDAD — Δ PV Neto ante cambios de tasa
B31: Escenario | C31: Tasa | D31: PV Neto | E31: Δ PV vs base | F31: Δ PV % | G31: Aprox. D_Mod × Δr × PV
B32: Base | C32: =C6 -> 0.06 | D32: =SUMPRODUCT(D14:D17*$C$5*(1-$C$8),1/((1+C32)^B14:B17)) -> 271273.39 | E32: — | F32: — | G32: —
B33: Sube 100bps | C33: =C6+C7 -> 0.07 | D33: =SUMPRODUCT(D14:D17*$C$5*(1-$C$8),1/((1+C33)^B14:B17)) -> 266973.23 | E33: =D33-D32 -> -4300.1522 | F33: =E33/D32 -> -0.015851729 | G33: =-C23*(C33-C6)*D32 -> -4363.9907
B34: Sube 200bps | C34: =C6+2*C7 -> 0.08 | D34: =SUMPRODUCT(D14:D17*$C$5*(1-$C$8),1/((1+C34)^B14:B17)) -> 262797.28 | E34: =D34-D32 -> -8476.1049 | F34: =E34/D32 -> -0.031245619 | G34: =-C23*(C34-C6)*D32 -> -8727.9814
B35: Baja 100bps | C35: =C6-C7 -> 0.05 | D35: =SUMPRODUCT(D14:D17*$C$5*(1-$C$8),1/((1+C35)^B14:B17)) -> 275703.02 | E35: =D35-D32 -> 4429.6387 | F35: =E35/D32 -> 0.016329058 | G35: =-C23*(C35-C6)*D32 -> 4363.9907
B36: Baja 200bps | C36: =C6-2*C7 -> 0.04 | D36: =SUMPRODUCT(D14:D17*$C$5*(1-$C$8),1/((1+C36)^B14:B17)) -> 280267.73 | E36: =D36-D32 -> 8994.3412 | F36: =E36/D32 -> 0.033156003 | G36: =-C23*(C36-C6)*D32 -> 8727.9814

Sheet 3_Comparacion
B1: COMPARACIÓN DE DURACIONES — AUTO vs CRÉDITO
B2: Fuentes: D'Arcy & Gorvett (2000) · Hodes & Feldblum (1996) · Noris (1985)
B4: Medida | C4: Auto RC (PPA Liability) | D4: Crédito / Caución | E4: Diferencia (Auto − Crédito) | F4: Referencia literatura
B5: Duración de Macaulay | C5: ='1_Auto_Duration'!C25 -> 2.1107826 | D5: ='2_Credito_Duration'!C21 -> 1.7052282 | E5: ='1_Auto_Duration'!C25-'2_Credito_Duration'!C21 -> 0.40555449 | F5: ~1.5 vs ~1.7 años
B6: Duración Modificada | C6: ='1_Auto_Duration'!C27 -> 2.0102692 | D6: ='2_Credito_Duration'!C23 -> 1.6087058 | E6: ='1_Auto_Duration'!C27-'2_Credito_Duration'!C23 -> 0.40156338 | F6: ~1.44 vs ~1.61 años
B7: Duración Efectiva | C7: ='1_Auto_Duration'!C32 -> 1.5122484 | D7: ='2_Credito_Duration'!C27 -> 1.6090393 | E7: ='1_Auto_Duration'!C31-'2_Credito_Duration'!C27 -> 0.40192925 | F7: ~1.09 vs ~1.53 años (D'Arcy 2000)
B8: Convexidad | C8: ='1_Auto_Duration'!C29 -> 7.6238108 | D8: ='2_Credito_Duration'!C25 -> 4.7723957 | E8: ='1_Auto_Duration'!C29-'2_Credito_Duration'!C25 -> 2.8514151 | F8: ~5.75 vs ~4.77
B11: INTERPRETACIÓN ECONÓMICA
B12: ¿Por qué Auto > Crédito en D_Modificada?
B13: La cola de auto liability es más larga: pagos médicos, litigios de daño corporal y gastos de ajuste se extienden hasta 10+ años. Crédito/Caución se liquida en 2-4 años.
B15: ¿Por qué D_Efectiva < D_Modificada en Auto?
B16: En auto, la inflación médica y de juicios está correlacionada con las tasas de interés. Cuando la tasa sube, la inflación sube también, aumentando los flujos nominales futuros. Esto reduce la sensibilidad neta del PV a la tasa. D'Arcy & Gorvett (2000) estiman que D_Efectiva ≈ 75% de D_Modificada con correlación ρ=40%.
B18: ¿Por qué D_Efectiva ≈ D_Modificada en Crédito?
B19: Las pérdidas por default no son sensibles a la inflación: el incumplimiento de un crédito depende del ciclo económico, no de los precios. Por eso no hay efecto inflacionario que reduzca la duración efectiva. Noris (1985) señala esta distinción explícitamente.
B21: Implicación para ALM (CUSF Cap. 5.4)
B22: Para el cálculo del Margen de Riesgo: MR = Base de Capital × 10% × D_Efectiva. Usar D_Modificada en lugar de D_Efectiva para auto sobreestima el margen ~25%. Para crédito, cualquiera de las dos medidas da resultados similares.
